neurox/__init__.py
neurox/analysis/__init__.py
neurox/analysis/corpus.py
neurox/analysis/plotting.py
neurox/analysis/visualization.py
neurox/data/__init__.py
neurox/data/annotate.py
neurox/data/loader.py
neurox/data/representations.py
neurox/data/utils.py
neurox/data/writer.py
neurox/data/extraction/__init__.py
neurox/data/extraction/transformers_extractor.py
neurox/interpretation/__init__.py
neurox/interpretation/ablation.py
neurox/interpretation/clustering.py
neurox/interpretation/linear_probe.py
neurox/interpretation/metrics.py
neurox/interpretation/probeless.py
neurox/interpretation/utils.py
neurox-1.0.9.dist-info/LICENSE
neurox-1.0.9.dist-info/METADATA
neurox-1.0.9.dist-info/WHEEL
neurox-1.0.9.dist-info/top_level.txt
neurox-1.0.9.dist-info/RECORD
