Metadata-Version: 2.1
Name: neurox
Version: 1.0.9
Summary: Toolkit for Neuron Analysis in Deep NLP Models
Home-page: https://github.com/fdalvi/NeuroX
Author: Fahim Dalvi
Author-email: faimaduddin@hbku.edu.qa
License: UNKNOWN
Project-URL: Documentation, https://neurox.qcri.org/docs/
Project-URL: Bug Tracker, https://github.com/fdalvi/NeuroX/issues
Platform: UNKNOWN
Classifier: Programming Language :: Python :: 3
Classifier: License :: OSI Approved :: BSD License
Classifier: Operating System :: OS Independent
Requires-Python: >=3.6
License-File: LICENSE
Requires-Dist: h5py (==3.1.0)
Requires-Dist: imbalanced-learn (==0.8)
Requires-Dist: matplotlib (==3.3.4)
Requires-Dist: numpy (==1.19.5)
Requires-Dist: scikit-learn (==0.24.2)
Requires-Dist: scipy (==1.5.4)
Requires-Dist: seaborn (==0.11.1)
Requires-Dist: svgwrite (==1.4.1)
Requires-Dist: tokenizers (==0.10.3)
Requires-Dist: torch (==1.8.1)
Requires-Dist: tqdm (==4.61.0)
Requires-Dist: transformers (==4.6.1)
